duneanalytics/__init__.py
duneanalytics/__version__.py
duneanalytics/duneanalytics.py
duneanalytics-2.0.0.dist-info/LICENSE
duneanalytics-2.0.0.dist-info/METADATA
duneanalytics-2.0.0.dist-info/WHEEL
duneanalytics-2.0.0.dist-info/top_level.txt
duneanalytics-2.0.0.dist-info/RECORD
