Metadata-Version: 2.1
Name: duneanalytics
Version: 2.0.0
Summary: Unofficial library for Dune Analytics.
Home-page: https://github.com/itzmestar/duneanalytics
Author: Tarique Anwer
Author-email: itzmetariq@gmail.com
License: Apache License 2.0
Classifier: Programming Language :: Python :: 3
Classifier: Programming Language :: Python :: 3.6
Classifier: Programming Language :: Python :: 3.7
Classifier: Programming Language :: Python :: 3.8
Classifier: Programming Language :: Python :: 3.9
Classifier: License :: OSI Approved :: Apache Software License
Classifier: Operating System :: OS Independent
License-File: LICENSE
Requires-Dist: requests (>=2.18.4)
